[{"id":"12","user_key":"12","world_key":"1","active_account":"1","tutorial":"5","nation_name":"goose's nation","nation_flag":"bfa74c756ebe5d9c101a703fc1a7e39d.jpg","leader_portrait":"default_leader_portrait.png","government":"2","last_government_switch":"0000-00-00 00:00:00","tax_rate":"30","military_budget":"0","entitlements_budget":"10","war_weariness":"23","color":"#FF0000","last_load":"2017-05-04 23:55:47","created":"2017-03-05 00:56:15","modified":"","land_count":"33","stats":{"population":"3026","culture":"6","gdp":"426","treasury":"-100","military":"100","support":129,"corruption_rate":10,"tax_income":116,"corruption_total":11,"military_spending":0,"military_after":200,"entitlements":12,"treasury_after":4,"entitlements_effect":6,"war_weariness":"23","building_maintenance":100},"effective_tax_rate":27,"functioning":true,"username":"goose"},{"id":"22","user_key":"14","world_key":"1","active_account":"1","tutorial":"3","nation_name":"jack Nation","nation_flag":"60febac1d9359201a99df7786c9cb845.png","leader_portrait":"e1fff195866979138c52718250d66fa6.jpg","government":"1","last_government_switch":"0000-00-00 00:00:00","tax_rate":"20","military_budget":"0","entitlements_budget":"0","war_weariness":"14","color":"#0F4761","last_load":"2017-05-04 23:54:21","created":"2017-04-29 16:59:38","modified":"","land_count":"14","stats":{"population":"712","culture":"5","gdp":"132","treasury":"0","military":"100","support":161,"corruption_rate":0,"tax_income":27,"corruption_total":0,"military_spending":0,"military_after":200,"entitlements":0,"treasury_after":27,"entitlements_effect":0,"war_weariness":"14","building_maintenance":0},"effective_tax_rate":20,"functioning":true,"username":"jack"},{"id":"17","user_key":"13","world_key":"1","active_account":"1","tutorial":"5","nation_name":"bob Nation","nation_flag":"default_nation_flag.png","leader_portrait":"default_leader_portrait.png","government":"1","last_government_switch":"0000-00-00 00:00:00","tax_rate":"0","military_budget":"0","entitlements_budget":"80","war_weariness":"0","color":"#1196F9","last_load":"2017-05-04 23:55:47","created":"2017-04-28 23:45:07","modified":"","land_count":"9","stats":{"population":"5608","culture":"25","gdp":"168","treasury":"0","military":"150","support":210,"corruption_rate":0,"tax_income":0,"corruption_total":0,"military_spending":0,"military_after":300,"entitlements":0,"treasury_after":0,"entitlements_effect":0,"war_weariness":"0","building_maintenance":0},"effective_tax_rate":0,"functioning":true,"username":"bob"},{"id":"27","user_key":"15","world_key":"1","active_account":"1","tutorial":"3","nation_name":"john Nation","nation_flag":"default_nation_flag.png","leader_portrait":"default_leader_portrait.png","government":"1","last_government_switch":"0000-00-00 00:00:00","tax_rate":"25","military_budget":"0","entitlements_budget":"25","war_weariness":"4","color":"#4CD326","last_load":"2017-05-04 23:54:21","created":"2017-04-29 21:48:15","modified":"","land_count":"4","stats":{"population":"603","culture":"5","gdp":"113","treasury":"0","military":"100","support":172,"corruption_rate":0,"tax_income":29,"corruption_total":0,"military_spending":0,"military_after":200,"entitlements":8,"treasury_after":21,"entitlements_effect":15,"war_weariness":"4","building_maintenance":0},"effective_tax_rate":25,"functioning":true,"username":"john"}]